nombre-0.2.0.dist-info/METADATA
nombre-0.2.0.dist-info/WHEEL
nombre/_types.py
nombre/_functions.py
nombre/__init__.py
nombre/py.typed
nombre/_nombre_rust.cpython-312-darwin.so
nombre-0.2.0.dist-info/RECORD
