Metadata-Version: 2.1
Name: nombre
Version: 0.2.0
Classifier: Programming Language :: Rust
Classifier: Programming Language :: Python :: Implementation :: CPython
Classifier: Programming Language :: Python :: Implementation :: PyPy
Requires-Dist: typing-extensions >=4.9.0 ; extra == 'test'
Provides-Extra: test
Summary: nombre is a utility for creating, parsing, and manipulating partition filenames
Home-Page: https://github.com/paradigmxyz/nombre
License: MIT OR Apache-2.0
Requires-Python: >=3.7
Project-URL: Documentation, https://github.com/paradigmxyz/nombre
Project-URL: Source, https://github.com/paradigmxyz/nombre
